fastapi_teams_bot/__init__.py
fastapi_teams_bot/bot.py
fastapi_teams_bot/config.py
fastapi_teams_bot/handlers.py
fastapi_teams_bot/types.py
fastapi_teams_bot-0.1.0.dist-info/METADATA
fastapi_teams_bot-0.1.0.dist-info/WHEEL
fastapi_teams_bot-0.1.0.dist-info/licenses/LICENSE
fastapi_teams_bot-0.1.0.dist-info/RECORD
