Metadata-Version: 2.4
Name: fastapi-teams-bot
Version: 0.1.0
Summary: FastAPI-based framework for building Microsoft Teams bots with pluggable message processing
Project-URL: Homepage, https://github.com/vishalgoel2/fastapi-teams-bot
Project-URL: Documentation, https://github.com/vishalgoel2/fastapi-teams-bot#readme
Project-URL: Repository, https://github.com/vishalgoel2/fastapi-teams-bot
Project-URL: Issues, https://github.com/vishalgoel2/fastapi-teams-bot/issues
Author-email: Vishal Goel <vishal@example.com>
License: MIT
License-File: LICENSE
Keywords: bot,chatbot,fastapi,langchain,langgraph,microsoft,teams
Classifier: Development Status :: 4 - Beta
Classifier: Framework :: FastAPI
Classifier: Intended Audience :: Developers
Classifier: License :: OSI Approved :: MIT License
Classifier: Programming Language :: Python :: 3
Classifier: Programming Language :: Python :: 3.10
Classifier: Programming Language :: Python :: 3.11
Classifier: Programming Language :: Python :: 3.12
Classifier: Topic :: Communications :: Chat
Classifier: Topic :: Software Development :: Libraries :: Python Modules
Requires-Python: >=3.10
Requires-Dist: aiohttp>=3.8.0
Requires-Dist: botbuilder-schema>=4.17.0
Requires-Dist: botframework-connector>=4.17.0
Requires-Dist: fastapi>=0.100.0
Provides-Extra: dev
Requires-Dist: black>=23.0.0; extra == 'dev'
Requires-Dist: httpx>=0.24.0; extra == 'dev'
Requires-Dist: mypy>=1.5.0; extra == 'dev'
Requires-Dist: pytest-asyncio>=0.21.0; extra == 'dev'
Requires-Dist: pytest-cov>=4.1.0; extra == 'dev'
Requires-Dist: pytest-mock>=3.11.0; extra == 'dev'
Requires-Dist: pytest>=7.4.0; extra == 'dev'
Requires-Dist: ruff>=0.1.0; extra == 'dev'
Requires-Dist: uvicorn>=0.23.0; extra == 'dev'
